MetaRpcMT4/__init__.py
MetaRpcMT4/mrpc_mt4_error_pb2.py
MetaRpcMT4/mrpc_mt4_error_pb2_grpc.py
MetaRpcMT4/mt4_account.py
MetaRpcMT4/mt4_term_api_account_helper_pb2.py
MetaRpcMT4/mt4_term_api_account_helper_pb2_grpc.py
MetaRpcMT4/mt4_term_api_charts_pb2.py
MetaRpcMT4/mt4_term_api_charts_pb2_grpc.py
MetaRpcMT4/mt4_term_api_connection_pb2.py
MetaRpcMT4/mt4_term_api_connection_pb2_grpc.py
MetaRpcMT4/mt4_term_api_health_check_pb2.py
MetaRpcMT4/mt4_term_api_health_check_pb2_grpc.py
MetaRpcMT4/mt4_term_api_internal_charts_pb2.py
MetaRpcMT4/mt4_term_api_internal_charts_pb2_grpc.py
MetaRpcMT4/mt4_term_api_market_info_pb2.py
MetaRpcMT4/mt4_term_api_market_info_pb2_grpc.py
MetaRpcMT4/mt4_term_api_subscriptions_pb2.py
MetaRpcMT4/mt4_term_api_subscriptions_pb2_grpc.py
MetaRpcMT4/mt4_term_api_trading_helper_pb2.py
MetaRpcMT4/mt4_term_api_trading_helper_pb2_grpc.py
metarpcmt4-0.0.81.dist-info/METADATA
metarpcmt4-0.0.81.dist-info/WHEEL
metarpcmt4-0.0.81.dist-info/top_level.txt
metarpcmt4-0.0.81.dist-info/RECORD
